primeutils/__init__.py
primeutils-1.0.dist-info/LICENSE
primeutils-1.0.dist-info/METADATA
primeutils-1.0.dist-info/WHEEL
primeutils-1.0.dist-info/top_level.txt
primeutils-1.0.dist-info/RECORD
